pnutty/nutty.py
pnutty-0.1.0.dist-info/licenses/LICENSE
pnutty-0.1.0.dist-info/METADATA
pnutty-0.1.0.dist-info/WHEEL
pnutty-0.1.0.dist-info/entry_points.txt
pnutty-0.1.0.dist-info/top_level.txt
pnutty-0.1.0.dist-info/RECORD
