Metadata-Version: 2.4
Name: pnutty
Version: 0.1.0
Summary: A TTY client application for pnut.io
Author-email: Morgan McMillian <morgan@mcmillian.dev>
Project-URL: Homepage, https://codeberg.org/spacenerdmo/pnutty
Project-URL: Bug Tracker, https://codeberg.org/spacenerdmo/pnutty/issues
Classifier: Programming Language :: Python :: 3
Classifier: License :: OSI Approved :: GNU General Public License v3 (GPLv3)
Classifier: Operating System :: OS Independent
Requires-Python: >=3.7
License-File: LICENSE
Requires-Dist: cmd2
Requires-Dist: pnutpy
Requires-Dist: tomlkit
Requires-Dist: requests
Requires-Dist: colorama
Requires-Dist: websockets>=11.0.3
Dynamic: license-file
